hello_cl_test/__init__.py
hello_cl_test-0.2.0.dist-info/METADATA
hello_cl_test-0.2.0.dist-info/WHEEL
hello_cl_test-0.2.0.dist-info/top_level.txt
hello_cl_test-0.2.0.dist-info/RECORD
