Metadata-Version: 2.4
Name: hello-cl-test
Version: 0.2.0
Summary: A simple Hello World package
Home-page: https://github.com/mukundprasadhscl/hello-cl
Author: Mukund Prasad H S
Author-email: mukund.hs@cirruslabs.io
Classifier: Programming Language :: Python :: 3
Classifier: License :: OSI Approved :: MIT License
Classifier: Operating System :: OS Independent
Requires-Python: >=3.7
Dynamic: author
Dynamic: author-email
Dynamic: classifier
Dynamic: description
Dynamic: description-content-type
Dynamic: home-page
Dynamic: requires-python
Dynamic: summary
